{
    "": [
        "W092901",
        "0704034",
        "0754604",
        "0705611",
        "0793594"
    ],
    "3F-1-A-1-f": [
        "0696940",
        "0713380",
        "0265118",
        "0744333",
        "0608584",
        "0087873",
        "0091065",
        "0361250",
        "0361251",
        "0671293",
        "0604483",
        "0741124",
        "0723493",
        "0679879",
        "0652182",
        "0730568",
        "0700621",
        "0711868",
        "0746876",
        "0688638",
        "0604681",
        "0620504",
        "0077992",
        "0625868",
        "0695324",
        "0650388",
        "0063164",
        "0360855",
        "0360856",
        "0366373",
        "0729570"
    ],
    "3F-1-A-2-f": [
        "W122370",
        "W035084",
        "W108304",
        "W027272",
        "W087772",
        "W085932",
        "W117951",
        "W123860",
        "W123861",
        "W122935",
        "W124858",
        "W124859",
        "W125113",
        "W125114",
        "W112082",
        "W114003",
        "W125148",
        "W116090",
        "W049824",
        "W027726",
        "W035702",
        "W049517",
        "W119959",
        "W089013",
        "W123963",
        "W124523",
        "W104807"
    ],
    "3F-1-A-3-f": [
        "0196389",
        "0196390",
        "0190606",
        "0322758",
        "0322759",
        "0205571",
        "0636738",
        "0096397",
        "0096398",
        "0193958",
        "0386133",
        "0198368",
        "0199603",
        "0776201",
        "0399043",
        "0399044",
        "0207336",
        "0332905",
        "0724036",
        "0183875",
        "0183876",
        "0331038",
        "0331039",
        "0331040",
        "0226927",
        "0226928",
        "0096284",
        "0096286",
        "0096287",
        "0096289",
        "0224439",
        "0389605",
        "0185794",
        "0626161",
        "0334793"
    ],
    "3F-1-A-4-f": [
        "0036720",
        "0715134",
        "0184872",
        "0334807",
        "0270492",
        "0089666",
        "0689869",
        "0212778",
        "0059048",
        "0079634",
        "0091093",
        "0119236",
        "0652250",
        "0663607",
        "0397625",
        "0659402",
        "0714098",
        "0226120",
        "0226539",
        "0119240",
        "0119245",
        "0610369",
        "0680971",
        "0267742",
        "0393569",
        "0711933",
        "0261001",
        "0261002",
        "0687138",
        "0769925"
    ],
    "3F-1-A-5-f": [
        "0756709",
        "0775101",
        "0787748",
        "0096672",
        "0310550",
        "0714151",
        "0229935",
        "0229936",
        "0707642",
        "0068583",
        "0160361",
        "0631158",
        "0062052",
        "0718652",
        "0087735",
        "0062309",
        "0071164",
        "0684872",
        "0062092",
        "0270454",
        "0703243",
        "0333452",
        "0615240",
        "0631159"
    ],
    "3F-1-A-6-f": [
        "W125009",
        "W125250",
        "W125251",
        "W114720",
        "W114721",
        "W114722",
        "W114723",
        "W114724",
        "W114725",
        "W114726",
        "W114727",
        "W114728",
        "W114729",
        "W086731",
        "W089254",
        "W075817",
        "W105474",
        "W030128",
        "W030129",
        "W075053",
        "W116661",
        "W077855",
        "0703281",
        "0704068",
        "0731754",
        "0601175",
        "0639514"
    ],
    "3F-1-A-7-f": [
        "0766034",
        "0766557",
        "0713374",
        "0737248",
        "0398959",
        "0350971",
        "0350972",
        "0172231",
        "0214774",
        "0259512",
        "0699100",
        "0177981",
        "0159757",
        "0159222",
        "0642050",
        "0705608",
        "0209696",
        "0396042",
        "0600086",
        "0647644",
        "0680990",
        "0605505",
        "0350106",
        "0350107",
        "0376627",
        "0376630",
        "0320275",
        "0320276",
        "0320277",
        "0389473",
        "0611965"
    ],
    "3F-1-A-8-f": [
        "0759399",
        "0721951",
        "0757987",
        "0189182",
        "0376812",
        "0777420",
        "0235904",
        "0680967",
        "0376831",
        "0686428",
        "0688528",
        "0729024",
        "0686306",
        "0654701",
        "0654702",
        "0388478",
        "0710821",
        "0741041",
        "0741042",
        "0741043",
        "0741044",
        "0741045",
        "0741046",
        "0322272",
        "0322273",
        "0647279",
        "0647280",
        "0647281",
        "0647282",
        "0711546",
        "0122480",
        "0637403",
        "0663715",
        "0094440",
        "0706883",
        "0780998",
        "0310813"
    ],
    "3F-1-B-1-f": [
        "0613171",
        "0347871",
        "0347872",
        "0319231",
        "0332725",
        "0360477",
        "0360478",
        "0752364",
        "0637011",
        "0738291",
        "0386117",
        "0318399",
        "0032096",
        "0697956",
        "0722231",
        "0722234",
        "0722463",
        "0333953",
        "0339644",
        "0344926",
        "0344927",
        "0722539",
        "0044438",
        "0710442",
        "0711044",
        "0692118",
        "0258267"
    ],
    "3F-1-B-2-f": [
        "0178100",
        "0178289",
        "0178099",
        "0360124",
        "0393192",
        "0377766",
        "0063753",
        "0784573",
        "0784574",
        "0784745",
        "0784746",
        "0785750",
        "0785752",
        "0787392",
        "0787393",
        "0787513",
        "0787514",
        "0791051",
        "0789829",
        "0789830",
        "0261500",
        "0647886",
        "0647887",
        "0743244",
        "0682751",
        "0682752",
        "0725671",
        "0725672",
        "0333471",
        "0756784"
    ],
    "3F-1-B-3-f": [
        "0372883",
        "0372884",
        "0372885",
        "0372886",
        "0640383",
        "0603620",
        "0369602",
        "0394871",
        "0614818",
        "0619928",
        "0382706",
        "0387080",
        "0368172",
        "0309945",
        "0309946",
        "0309947",
        "0309948",
        "0310297",
        "0310298",
        "0310299",
        "0637584",
        "0382604",
        "0357609",
        "0364095",
        "0308090",
        "0393538",
        "0633089",
        "0633090",
        "0367135",
        "0367136",
        "0368180"
    ],
    "3F-1-B-4-f": [
        "0722268",
        "0722269",
        "0682316",
        "0682753",
        "0712869",
        "0719902",
        "0381174",
        "0383208",
        "0385359",
        "0077963",
        "0077966",
        "0392351",
        "0633971",
        "0633972",
        "0686442",
        "0690312",
        "0390776",
        "0398092",
        "0132990",
        "0132991",
        "0707129",
        "0706973",
        "0733412",
        "0742198",
        "0751774",
        "0782229",
        "0644802",
        "0648325"
    ],
    "3F-1-B-5-f": [
        "0762303",
        "0762289",
        "0762153",
        "0771986",
        "0673417",
        "0264301",
        "0716644",
        "0608396",
        "0698150",
        "0698151",
        "0698152",
        "0698153",
        "0698154",
        "0698155",
        "0698156",
        "0698157",
        "0698158",
        "0679019",
        "0262765",
        "0262766",
        "0702051"
    ],
    "3F-1-B-6-f": [
        "0675023",
        "0347600",
        "0347601",
        "0663474",
        "0671362",
        "0677429",
        "0729334",
        "0705406",
        "0708576",
        "0751710",
        "0348226",
        "0351878",
        "0745336",
        "0397097",
        "0678095",
        "0729036",
        "0314667",
        "0775041",
        "0663570",
        "0180427",
        "0652005",
        "0652006",
        "0784548",
        "0336260",
        "0312710",
        "0257914",
        "0711125",
        "0729709",
        "0633238",
        "0743202",
        "0387373",
        "0683609"
    ],
    "3F-1-B-7-f": [
        "0178935",
        "0178936",
        "0199898",
        "0696072",
        "0689598",
        "0237006",
        "0237007",
        "0237008",
        "0237009",
        "0237010",
        "0723084",
        "0723262",
        "0723263",
        "0396501",
        "0264698",
        "0264699",
        "0743153",
        "0609443",
        "0193038",
        "0642444",
        "0695995",
        "0665170",
        "0261584",
        "0081099",
        "0365273",
        "0365274",
        "0339039",
        "0788838",
        "0691299",
        "0712038"
    ],
    "3F-1-B-8-f": [
        "0778855",
        "0778855",
        "0731044",
        "0731044",
        "0616704",
        "0616704",
        "0389310",
        "0389310",
        "0367232",
        "0367232",
        "0399068",
        "0399068",
        "0755357",
        "0755357",
        "0757931",
        "0757931",
        "0762288",
        "0762288",
        "0373403",
        "0373403",
        "0742226",
        "0742226",
        "0775354",
        "0775354",
        "0685978",
        "0685978",
        "0789510",
        "0789510",
        "0348167",
        "0348167",
        "0096864",
        "0096864",
        "0687295",
        "0687295",
        "0381373",
        "0381373",
        "0390835",
        "0390835",
        "0763907",
        "0763907",
        "0669907",
        "0669907",
        "0774240",
        "0774240",
        "0703341",
        "0703341",
        "0678813",
        "0678813",
        "0766553",
        "0766553",
        "0090860",
        "0090860",
        "0745835",
        "0745835",
        "0265986",
        "0265986"
    ]
}